{
  "_class": "shapeGroup",
  "booleanOperation": -1,
  "clippingMaskMode": 0,
  "do_objectID": "CCBB16F4-A68D-4FB8-A9CB-190D634035B8",
  "exportOptions": {
    "_class": "exportOptions",
    "exportFormats": [
    ],
    "includedLayerIds": [
    ],
    "layerOptions": 0,
    "shouldTrim": false
  },
  "frame": {
    "_class": "rect",
    "constrainProportions": false,
    "do_objectID": "A5FE8D3D-F193-4F4B-AF75-92C609DF938E",
    "height": 22.5771484375,
    "width": 678.8092573323968,
    "x": 0.5820470154288842,
    "y": 0.4228515625
  },
  "groupLayout": {
    "_class": "MSImmutableFreeformGroupLayout"
  },
  "hasClickThrough": false,
  "hasClippingMask": true,
  "isFixedToViewport": false,
  "isFlippedHorizontal": false,
  "isFlippedVertical": false,
  "isLocked": false,
  "isVisible": true,
  "layerListExpandedType": 0,
  "layers": [
    {
      "class": "shapeGroup",
      "id": "05152CF4-2A98-4546-A372-2050ADB0D2BD"
    },
    {
      "class": "shapeGroup",
      "id": "6FF95CBB-46C0-4807-AD33-05607D654214"
    },
    {
      "class": "shapeGroup",
      "id": "4D32986F-9144-4133-99F3-BB771318D5EC"
    },
    {
      "class": "shapeGroup",
      "id": "5D88951C-28A1-4A14-BA7A-948A2964ACDD"
    },
    {
      "class": "shapeGroup",
      "id": "749286FC-47FD-44E5-9DA9-440A4DF10B54"
    },
    {
      "class": "shapeGroup",
      "id": "87D3C127-DAAA-4711-9030-42AD0C51F46F"
    },
    {
      "class": "shapeGroup",
      "id": "D48E6C31-E9F7-45EE-8991-BA79B5A27AFB"
    },
    {
      "class": "rectangle",
      "id": "1F468516-D126-470D-93C8-678FE68BA5FA"
    },
    {
      "class": "shapeGroup",
      "id": "82599398-747D-4FF8-8B54-A5F185615795"
    }
  ],
  "name": "Mask",
  "nameIsFixed": false,
  "resizingConstraint": 63,
  "resizingType": 0,
  "rotation": 0,
  "shouldBreakMaskChain": false,
  "style": {
    "_class": "style",
    "borders": [
      {
        "_class": "border",
        "color": {
          "_class": "color",
          "alpha": 1,
          "blue": 0.592,
          "green": 0.592,
          "red": 0.592
        },
        "fillType": 0,
        "gradient": {
          "_class": "gradient",
          "elipseLength": 0,
          "from": "{0.5, 0}",
          "gradientType": 0,
          "stops": [
            {
              "_class": "gradientStop",
              "color": {
                "_class": "color",
                "alpha": 1,
                "blue": 1,
                "green": 1,
                "red": 1
              },
              "position": 0
            },
            {
              "_class": "gradientStop",
              "color": {
                "_class": "color",
                "alpha": 1,
                "blue": 0.08235294117647059,
                "green": 0.2313725490196079,
                "red": 0.3294117647058823
              },
              "position": 1
            }
          ],
          "to": "{0.5, 1}"
        },
        "isEnabled": false,
        "position": 0,
        "thickness": 1
      }
    ],
    "contextSettings": {
      "_class": "graphicsContextSettings",
      "blendMode": 0,
      "do_objectID": "FEC306AD-C020-467D-B49B-9CED4A35FB49",
      "opacity": 0
    },
    "do_objectID": "C7698465-D02B-418A-978C-09F2AE1CAC83",
    "endMarkerType": 0,
    "fills": [
      {
        "_class": "fill",
        "color": {
          "_class": "color",
          "alpha": 1,
          "blue": 0.592,
          "green": 0.592,
          "red": 0.592
        },
        "fillType": 0,
        "gradient": {
          "_class": "gradient",
          "elipseLength": 0,
          "from": "{0.5, 0}",
          "gradientType": 0,
          "stops": [
            {
              "_class": "gradientStop",
              "color": {
                "_class": "color",
                "alpha": 1,
                "blue": 1,
                "green": 1,
                "red": 1
              },
              "position": 0
            },
            {
              "_class": "gradientStop",
              "color": {
                "_class": "color",
                "alpha": 1,
                "blue": 0.08235294117647059,
                "green": 0.2313725490196079,
                "red": 0.3294117647058823
              },
              "position": 1
            }
          ],
          "to": "{0.5, 1}"
        },
        "isEnabled": true,
        "noiseIndex": 0,
        "noiseIntensity": 0,
        "patternFillType": 1,
        "patternTileScale": 1
      }
    ],
    "miterLimit": 10,
    "startMarkerType": 0,
    "windingRule": 0
  },
  "userInfo": {
    "com.animaapp.stc-sketch-plugin": {
      "kModelPropertiesKey": {
      }
    }
  },
  "windingRule": 0
}